tronclinet/__init__.py
tronclinet/main.py
tronclinet-0.0.1.dist-info/LICENSE.txt
tronclinet-0.0.1.dist-info/METADATA
tronclinet-0.0.1.dist-info/WHEEL
tronclinet-0.0.1.dist-info/top_level.txt
tronclinet-0.0.1.dist-info/RECORD
