Metadata-Version: 2.1
Name: tronclinet
Version: 0.0.1
Summary: tronclinet library for Python
Author: maxtron
Author-email: cijavi4719@bariswc.com
License: MIT
Project-URL: Source Repository, https://github.com
License-File: LICENSE.txt
Requires-Dist: requests
